Metadata-Version: 2.1
Name: tsc-cfg
Version: 0.5
Summary: 自定义的配置文件
Home-page: https://github.com/aitsc/tsc-cfg
Author: aitsc
License: GPLv3
Keywords: tools
Classifier: Intended Audience :: Developers
Classifier: License :: OSI Approved :: GNU General Public License v3 (GPLv3)
Classifier: Programming Language :: Python :: 3 :: Only
Classifier: Topic :: Software Development :: Libraries
Requires-Python: >=3.7
Provides-Extra: recommended
License-File: LICENSE
